{
  "updated_at": "2026-03-20T15:51:24+0900",
  "config": {
    "margin_mode": "ISOLATED",
    "leverage": 3,
    "max_positions": 6,
    "order_notional_usdt": 40
  },
  "pnl": {
    "realized_gross": 4.845599999999999,
    "commission": -3.0720000000000014,
    "realized_net": 1.7735999999999978,
    "unrealized": -0.3316268200000062,
    "total": 1.4419731799999917
  },
  "positions": [
    {
      "symbol": "AGTUSDT",
      "side": "LONG",
      "qty": 17201.0,
      "entry": 0.006976,
      "mark": 0.006993,
      "unrealized_pnl": 0.29241699999999404,
      "order_id": 1773968397370
    },
    {
      "symbol": "NEIROUSDT",
      "side": "SHORT",
      "qty": 1835423.0,
      "entry": 6.538e-05,
      "mark": 6.572e-05,
      "unrealized_pnl": -0.6240438200000002,
      "order_id": 1773974020149
    }
  ]
}