{
  "updated_at": "2026-03-20T18:15:15+0900",
  "config": {
    "margin_mode": "ISOLATED",
    "leverage": 3,
    "max_positions": 6,
    "order_notional_usdt": 40
  },
  "pnl": {
    "realized_gross": -1.0284000000000004,
    "commission": -3.840000000000002,
    "realized_net": -4.868400000000003,
    "unrealized": -10.75768617000001,
    "total": -15.626086170000013
  },
  "positions": [
    {
      "symbol": "AGTUSDT",
      "side": "LONG",
      "qty": 17201.0,
      "entry": 0.006976,
      "mark": 0.006351,
      "unrealized_pnl": -10.75062500000001,
      "order_id": 1773968397370
    },
    {
      "symbol": "NEIROUSDT",
      "side": "SHORT",
      "qty": 1835423.0,
      "entry": 6.538e-05,
      "mark": 6.517e-05,
      "unrealized_pnl": 0.3854388299999994,
      "order_id": 1773974020149
    },
    {
      "symbol": "METUSDT",
      "side": "SHORT",
      "qty": 785.0,
      "entry": 0.1528,
      "mark": 0.1533,
      "unrealized_pnl": -0.39250000000000035,
      "order_id": 1773990160961
    }
  ]
}