{
  "updated_at": "2026-03-20T18:01:34+0900",
  "config": {
    "margin_mode": "ISOLATED",
    "leverage": 3,
    "max_positions": 6,
    "order_notional_usdt": 40
  },
  "pnl": {
    "realized_gross": 1.5695999999999997,
    "commission": -3.648000000000002,
    "realized_net": -2.078400000000002,
    "unrealized": -11.765875940000006,
    "total": -13.844275940000008
  },
  "positions": [
    {
      "symbol": "AGTUSDT",
      "side": "LONG",
      "qty": 17201.0,
      "entry": 0.006976,
      "mark": 0.006295,
      "unrealized_pnl": -11.713881000000002,
      "order_id": 1773968397370
    },
    {
      "symbol": "NEIROUSDT",
      "side": "SHORT",
      "qty": 1835423.0,
      "entry": 6.538e-05,
      "mark": 6.516e-05,
      "unrealized_pnl": 0.40379305999998993,
      "order_id": 1773974020149
    },
    {
      "symbol": "METUSDT",
      "side": "SHORT",
      "qty": 785.0,
      "entry": 0.1528,
      "mark": 0.1535,
      "unrealized_pnl": -0.5495000000000049,
      "order_id": 1773990160961
    },
    {
      "symbol": "JCTUSDT",
      "side": "LONG",
      "qty": 46856.0,
      "entry": 0.002561,
      "mark": 0.002563,
      "unrealized_pnl": 0.09371200000001244,
      "order_id": 1773997173575
    }
  ]
}